pyquibase/__init__.py
pyquibase/liquibase_executor.py
pyquibase/pyquibase.py
pyquibase/db-connectors/mysql-connector-java-5.1.42-bin.jar
pyquibase/db-connectors/postgresql-42.1.3.jar
pyquibase/db-connectors/sqlite-jdbc-3.18.0.jar
pyquibase/liquibase/liquibase.jar
pyquibase/liquibase/lib/snakeyaml-1.13.jar
mzc_sample-1.2.dist-info/LICENSE
mzc_sample-1.2.dist-info/METADATA
mzc_sample-1.2.dist-info/WHEEL
mzc_sample-1.2.dist-info/top_level.txt
mzc_sample-1.2.dist-info/RECORD
