Metadata-Version: 2.1
Name: mzc-sample
Version: 1.2
Summary: Python wrapper for liquibase
Home-page: https://github.com/rampart81/pyquibase
Author: Eun Woo Song
Author-email: songew@gmail.com
License: UNKNOWN
Download-URL: https://github.com/rampart81/pyquibase/archive/1.2.tar.gz
Keywords: liquibase,db migration
Platform: UNKNOWN
Classifier: Programming Language :: Python :: 3
Classifier: Programming Language :: Python :: 3.2
Classifier: Programming Language :: Python :: 3.3
Classifier: Programming Language :: Python :: 3.4
Classifier: Programming Language :: Python :: 3.5
Classifier: Programming Language :: Python :: 3.6
Requires-Python: >=3
